{
  "assessmentCollection": [
    {
      "id": "001360ab-ff6e-4875-9e90-6ea0820ad28f",
      "memberid": "78cfef9f-a6db-4c6b-b514-a0c4b57c1b5f",
      "weight": "45",
      "chest": "45",
      "thigh": "34",
      "upperArm": "34",
      "waist": "34",
      "hips": "34",
      "date": "8/26/2019, 5:59:22 PM",
      "trainerComment": "come on"
    },
    {
      "id": "073c6f87-0aac-43d8-8e25-3e86521dd46e",
      "memberid": "af630aa1-eb22-4d7b-8519-24e4898fbbdb",
      "weight": "100",
      "chest": "23",
      "thigh": "12",
      "upperArm": "12",
      "waist": "12",
      "hips": "45",
      "date": "8/26/2019, 11:37:22 PM",
      "trainerComment": ""
    },
    {
      "id": "eb641c72-1a55-4acc-b327-056261be7c3f",
      "memberid": "af630aa1-eb22-4d7b-8519-24e4898fbbdb",
      "weight": "100",
      "chest": "23",
      "thigh": "12",
      "upperArm": "55",
      "waist": "23",
      "hips": "45",
      "date": "8/26/2019, 11:37:07 PM",
      "trainerComment": "well done"
    }
  ]
}